MANIFEST.in
setup.py
admin_skel/__init__.py
admin_skel/management/__init__.py
admin_skel/management/commands/__init__.py
admin_skel/management/commands/runserver.py
admin_skel/media/css/print.css
admin_skel/media/css/reset.css
admin_skel/media/css/style.css
admin_skel/media/humanmsg/humanmsg.css
admin_skel/media/humanmsg/humanmsg.js
admin_skel/media/images/plus.png
admin_skel/media/images/admin/plus.png
admin_skel/media/js/rounded-corners-min.js
admin_skel/media/js/jquery/jquery-1.6.2.min.js
admin_skel/media/js/jquery/jquery.easing.1.3.js
admin_skel/templates/admin_skel/attachment_delete.html
admin_skel/templates/admin_skel/base.html
admin_skel/templates/admin_skel/index.html
admin_skel/templates/admin_skel/login.html
admin_skel/templates/admin_skel/logout.html
admin_skel/templatetags/__init__.py
admin_skel/templatetags/admin_media.py
django_admin_skel.egg-info/PKG-INFO
django_admin_skel.egg-info/SOURCES.txt
django_admin_skel.egg-info/dependency_links.txt
django_admin_skel.egg-info/not-zip-safe
django_admin_skel.egg-info/top_level.txt