Metadata-Version: 1.0
Name: django-admin-skel
Version: 1.0.8
Summary: Basic admin styles for django (non django.contrib.admin). Maintained by Alexey Loshkarev <alexey@smscoin.com>
Home-page: http://pypi.python.org/pypi/django-admin-skel/
Author: Andrey Shuster
Author-email: andrey@smscoin.com
License: GPL
Platform: UNKNOWN
Classifier: Development Status :: 5 - Production/Stable
Classifier: Intended Audience :: Developers
Classifier: License :: OSI Approved :: GNU General Public License (GPL)
Classifier: Natural Language :: English
Classifier: Programming Language :: Python
Classifier: Topic :: Software Development :: Libraries :: Python Modules
